flexconf/__init__.py
flexconf/__main__.py
flexconf/flexconf.py
flexconf-1.0.4.dist-info/METADATA
flexconf-1.0.4.dist-info/WHEEL
flexconf-1.0.4.dist-info/top_level.txt
flexconf-1.0.4.dist-info/RECORD
